easy_pil/__init__.py
easy_pil/_version.py
easy_pil/aio_editor.py
easy_pil/canvas.py
easy_pil/editor.py
easy_pil/font.py
easy_pil/fonts/caveat/caveat.ttf
easy_pil/fonts/montserrat/montserrat_bold.ttf
easy_pil/fonts/montserrat/montserrat_italic.ttf
easy_pil/fonts/montserrat/montserrat_light.ttf
easy_pil/fonts/montserrat/montserrat_regular.ttf
easy_pil/fonts/poppins/poppins_bold.ttf
easy_pil/fonts/poppins/poppins_italic.ttf
easy_pil/fonts/poppins/poppins_light.ttf
easy_pil/fonts/poppins/poppins_regular.ttf
easy_pil/gif_editor.py
easy_pil/text.py
easy_pil/types/__init__.py
easy_pil/types/common.py
easy_pil/types/workspace.py
easy_pil/utils.py
easy_pil/workspace.py
easy_pil-0.3.9.dist-info/LICENSE
easy_pil-0.3.9.dist-info/METADATA
easy_pil-0.3.9.dist-info/WHEEL
easy_pil-0.3.9.dist-info/RECORD
