Metadata-Version: 2.1
Name: easy-pil
Version: 0.3.9
Summary: A Python library built on top of PIL to easily edit/modify images
Home-page: https://github.com/shahriyardx/easy-pil
Keywords: easy-pil,easy pillow,Pillow,image editing
Author: Md Shahriyar Alam
Author-email: mdshahriyaralam552@gmail.com
Requires-Python: >=3.8.1,<3.15
Classifier: Development Status :: 5 - Production/Stable
Classifier: Intended Audience :: Developers
Classifier: License :: OSI Approved :: MIT License
Classifier: Programming Language :: Python :: 3
Classifier: Programming Language :: Python :: 3.9
Classifier: Programming Language :: Python :: 3.10
Classifier: Programming Language :: Python :: 3.11
Classifier: Programming Language :: Python :: 3.7
Classifier: Programming Language :: Python :: 3.8
Classifier: Topic :: Software Development :: Build Tools
Requires-Dist: aiocache (>=0.12.2,<0.13.0)
Requires-Dist: aiohttp (>=3.10.5,<4.0.0)
Requires-Dist: pillow (>=10.1.0,<11.0.0)
Requires-Dist: requests (>=2.30.0,<3.0.0)
Requires-Dist: typing-extensions (>=4.8.0,<5.0.0)
Project-URL: Documentation, https://easy-pil.readthedocs.io/en/latest/
Project-URL: Repository, https://github.com/shahriyardx/easy-pil
